{
  "$schema": "../../../node_modules/@angular-devkit/schematics/collection-schema.json",
  "schematics": {
    "ng-add": {
      "factory": "./add-checkout/index#addCheckoutFeatures",
      "description": "Add and configure Spartacus' Checkout library",
      "schema": "./add-checkout/schema.json",
      "private": true,
      "hidden": true,
      "aliases": ["install"]
    },
    "add-spartacus-library": {
      "description": "Install a spartacus library",
      "factory": "./add-library/index#addSpartacusLibrary",
      "private": true,
      "hidden": true
    },
    "add": {
      "factory": "./add-checkout/index#addCheckoutFeatures",
      "description": "Add and configure Spartacus' Checkout library",
      "schema": "./add-checkout/schema.json"
    }
  }
}
